graphql_server/__init__.py
graphql_server/aiohttp/__init__.py
graphql_server/aiohttp/test/__init__.py
graphql_server/aiohttp/test/client.py
graphql_server/aiohttp/views.py
graphql_server/asgi/__init__.py
graphql_server/asgi/test/__init__.py
graphql_server/asgi/test/client.py
graphql_server/chalice/__init__.py
graphql_server/chalice/views.py
graphql_server/channels/__init__.py
graphql_server/channels/handlers/__init__.py
graphql_server/channels/handlers/base.py
graphql_server/channels/handlers/http_handler.py
graphql_server/channels/handlers/ws_handler.py
graphql_server/channels/router.py
graphql_server/channels/testing.py
graphql_server/django/__init__.py
graphql_server/django/context.py
graphql_server/django/test/__init__.py
graphql_server/django/test/client.py
graphql_server/django/views.py
graphql_server/exceptions.py
graphql_server/fastapi/__init__.py
graphql_server/fastapi/context.py
graphql_server/fastapi/router.py
graphql_server/file_uploads/__init__.py
graphql_server/file_uploads/scalars.py
graphql_server/file_uploads/utils.py
graphql_server/flask/__init__.py
graphql_server/flask/views.py
graphql_server/http/__init__.py
graphql_server/http/async_base_view.py
graphql_server/http/base.py
graphql_server/http/exceptions.py
graphql_server/http/ides.py
graphql_server/http/parse_content_type.py
graphql_server/http/sync_base_view.py
graphql_server/http/temporal_response.py
graphql_server/http/types.py
graphql_server/http/typevars.py
graphql_server/litestar/__init__.py
graphql_server/litestar/controller.py
graphql_server/py.typed
graphql_server/quart/__init__.py
graphql_server/quart/views.py
graphql_server/runtime.py
graphql_server/sanic/__init__.py
graphql_server/sanic/utils.py
graphql_server/sanic/views.py
graphql_server/static/apollo-sandbox.html
graphql_server/static/graphiql.html
graphql_server/static/pathfinder.html
graphql_server/subscriptions/__init__.py
graphql_server/subscriptions/protocols/__init__.py
graphql_server-3.0.0.dist-info/WHEEL
graphql_server-3.0.0.dist-info/METADATA
graphql_server-3.0.0.dist-info/RECORD
