Metadata-Version: 2.3
Name: graphql-server
Version: 3.0.0
Summary: A library setting up a GraphQL server in a variety of frameworks
Keywords: graphql,api,rest,starlette,async,fastapi,django,flask,litestar,sanic,channels,aiohttp,chalice,webob,pyright,mypy,codeflash
Author: Syrus Akbary
Author-email: Syrus Akbary <me@syrusakbary.com>
License: MIT
Classifier: Development Status :: 5 - Production/Stable
Classifier: Intended Audience :: Developers
Classifier: Topic :: Software Development :: Libraries
Classifier: Topic :: Software Development :: Libraries :: Python Modules
Classifier: License :: OSI Approved :: MIT License
Requires-Dist: graphql-core>=3.2.0,<3.4.0
Requires-Dist: aiohttp>=3.7.4.post0,<4 ; extra == 'aiohttp'
Requires-Dist: starlette>=0.18.0 ; extra == 'asgi'
Requires-Dist: python-multipart>=0.0.7 ; extra == 'asgi'
Requires-Dist: chalice~=1.22 ; extra == 'chalice'
Requires-Dist: channels>=3.0.5 ; extra == 'channels'
Requires-Dist: asgiref~=3.2 ; extra == 'channels'
Requires-Dist: rich>=12.0.0 ; extra == 'debug'
Requires-Dist: libcst ; extra == 'debug'
Requires-Dist: starlette>=0.18.0 ; extra == 'debug-server'
Requires-Dist: uvicorn>=0.11.6 ; extra == 'debug-server'
Requires-Dist: websockets>=15.0.1,<16 ; extra == 'debug-server'
Requires-Dist: python-multipart>=0.0.7 ; extra == 'debug-server'
Requires-Dist: typer>=0.7.0 ; extra == 'debug-server'
Requires-Dist: pygments~=2.3 ; extra == 'debug-server'
Requires-Dist: rich>=12.0.0 ; extra == 'debug-server'
Requires-Dist: libcst ; extra == 'debug-server'
Requires-Dist: django>=3.2 ; extra == 'django'
Requires-Dist: asgiref~=3.2 ; extra == 'django'
Requires-Dist: fastapi>=0.65.2 ; extra == 'fastapi'
Requires-Dist: python-multipart>=0.0.7 ; extra == 'fastapi'
Requires-Dist: flask>=1.1 ; extra == 'flask'
Requires-Dist: litestar>=2 ; python_full_version >= '3.10' and python_full_version < '4' and extra == 'litestar'
Requires-Dist: opentelemetry-api<2 ; extra == 'opentelemetry'
Requires-Dist: opentelemetry-sdk<2 ; extra == 'opentelemetry'
Requires-Dist: pyinstrument>=4.0.0 ; extra == 'pyinstrument'
Requires-Dist: quart>=0.19.3 ; extra == 'quart'
Requires-Dist: sanic>=20.12.2 ; extra == 'sanic'
Requires-Dist: webob>=1.8 ; extra == 'webob'
Requires-Python: >=3.9, <4.0
Project-URL: Changelog, https://github.com/graphql-python/graphql-server/changelog
Project-URL: homepage, https://graphql-server.org/
Project-URL: repository, https://github.com/graphql-python/graphql-server
Provides-Extra: aiohttp
Provides-Extra: asgi
Provides-Extra: chalice
Provides-Extra: channels
Provides-Extra: debug
Provides-Extra: debug-server
Provides-Extra: django
Provides-Extra: fastapi
Provides-Extra: flask
Provides-Extra: litestar
Provides-Extra: opentelemetry
Provides-Extra: pyinstrument
Provides-Extra: quart
Provides-Extra: sanic
Provides-Extra: webob
